{
  "version": "1.0.0",
  "rss": "https://raw.githubusercontent.com/Kome-Lab/KomeModPacks/news/news.rss",
  "discord": {
    "clientId": "1079280155580694600",
    "smallImageText": "KomeModLauncher",
    "smallImageKey": "pack_kome"
  },
  "servers": [
    {
      "id": "1.Vplayer-1.16.5",
      "name": "%0%Vplayer-1.16.5 (Minecraft 1.16.5)",
      "description": "動画鑑賞が出来るModが導入されています",
      "icon": "https://raw.githubusercontent.com/Kome-Lab/KomeModPacks/deploy/servers/1.Vplayer-1.16.5/pack.png",
      "version": "1.0.1",
      "address": "",
      "minecraftVersion": "1.16.5",
      "discord": {
        "shortId": "KomeModLauncher",
        "largeImageText": "VplayerMod",
        "largeImageKey": "pack_v"
      },
      "mainServer": false,
      "autoconnect": false,
      "modules": [
        {
          "id": "net.minecraftforge:forge:1.16.5-36.2.34:installer",
          "name": "Minecraft Forge (installer)",
          "type": "Forge",
          "artifact": {
            "size": 7947907,
            "MD5": "D6CCFB3B5AB20BBE021FE243B8CA773C",
            "url": "https://raw.githubusercontent.com/Kome-Lab/KomeModPacks/deploy/repo/lib/net/minecraftforge/forge/1.16.5-36.2.34/forge-1.16.5-36.2.34-installer.jar"
          },
          "subModules": []
        },
        {
          "id": "net.kunmc.lab:vplayer:1.3-1.16.5-SNAPSHOT@jar",
          "name": "VideoPlayer",
          "type": "ForgeMod",
          "artifact": {
            "size": 41076744,
            "url": "https://raw.githubusercontent.com/Kome-Lab/KomeModPacks/deploy/servers/1.Vplayer-1.16.5/forgemods/optionalon/vplayer-1.3-1.16.5-SNAPSHOT-all.jar",
            "MD5": "7ebcb4fcda1a20e3bf54bb4bbcd01724"
          },
          "required": {
            "value": true
          }
        },
        {
          "id": "technicianlp.reauth:ReAuth-1.16-Forge-4.0.7@jar",
          "name": "ReAuth",
          "type": "ForgeMod",
          "artifact": {
            "size": 169698,
            "url": "https://raw.githubusercontent.com/Kome-Lab/KomeModPacks/deploy/servers/1.Vplayer-1.16.5/forgemods/optionalon/ReAuth-1.16-Forge-4.0.7.jar",
            "MD5": "7270E3AB226B205DEDF9DE05321353C9"
          },
          "required": {
            "value": false
          }
        }
      ]
    }
  ]
}
